good_cache/__init__.py
good_cache/cache.py
good_cache/utils.py
good_cache-0.1.32.dist-info/LICENSE
good_cache-0.1.32.dist-info/METADATA
good_cache-0.1.32.dist-info/WHEEL
good_cache-0.1.32.dist-info/top_level.txt
good_cache-0.1.32.dist-info/RECORD
