Metadata-Version: 2.1
Name: good-cache
Version: 0.1.32
Summary: Efficient function output caching based on input files and other parameters to the function.
Home-page: https://github.com/arunsundaram50/good-cache.git
Author: Arun Sundaram
Author-email: arun_co@yahoo.com
License-File: LICENSE
Requires-Dist: send2trash
Requires-Dist: pandas
